omacase/__init__.py
omacase/__main__.py
omacase/alignment.py
omacase/annotation_viewer.py
omacase/annotations.py
omacase/app.py
omacase/config_editor.py
omacase/dashboard.py
omacase/dataviz.py
omacase/layouts.py
omacase/omviewer.py
omacase/opmap.py
omacase/param_parser.py
omacase/portal.py
omacase/repeat_caller.py
omacase/repeat_simulator.py
omacase/report.py
omacase/utils.py
omacase/assets/css/00_bootstrap.min.css
omacase/assets/css/00_bootstrap.min.css.map
omacase/assets/css/01_omacase.css
omacase/assets/js/bootstrap.bundle.min.js
omacase/assets/js/bootstrap.bundle.min.js.map
omacase/config/default.toml
omacase-1.0.dist-info/LICENSE.md
omacase-1.0.dist-info/METADATA
omacase-1.0.dist-info/WHEEL
omacase-1.0.dist-info/top_level.txt
omacase-1.0.dist-info/RECORD
