Metadata-Version: 2.1
Name: omacase
Version: 1.0
Summary: a tool to analyze optical mapping data, with _de novo_ repeat motif detection and analysis capabilities
Home-page: https://github.com/ccneko/OMACASE
Author: Claire Chung
Author-email: clairechung112@gmail.com
License: OMACASE, a tool to analyze optical mapping data with _de novo_ repeat motif detection and analysis capabilities 
Platform: any
Classifier: Programming Language :: Python :: 3 :: Only
Classifier: License :: OSI Approved :: GNU General Public License (GPL)
Classifier: Operating System :: OS Independent
Requires-Python: >=3.8
License-File: LICENSE.md
Requires-Dist: cython >=0.29.24
Requires-Dist: deepmerge >=1.0.1
Requires-Dist: dash >=2.0.0
Requires-Dist: dash-bootstrap-components >=0.12.2
Requires-Dist: dash-uploader >=0.6.0
Requires-Dist: filelock >=3.4.2
Requires-Dist: gevent >=21.1.2
Requires-Dist: grpcio >=1.43.0
Requires-Dist: holoviews >=1.14.8
Requires-Dist: intervaltree >=3.1.0
Requires-Dist: Jinja2 ==2.11.2
Requires-Dist: kaleido >=0.2.1
Requires-Dist: matplotlib >=3.4.3
Requires-Dist: modin >=0.13.2
Requires-Dist: markupsafe ==2.0.1
Requires-Dist: msgpack >=1.0.3
Requires-Dist: numba >=0.55.1
Requires-Dist: numpy >=1.21.3
Requires-Dist: pandas >=1.2.4
Requires-Dist: pdfkit >=1.0.0
Requires-Dist: protobuf >=3.19.4
Requires-Dist: plotly >=5.3.1
Requires-Dist: psutil >=5.9.0
Requires-Dist: ray >=1.11.0
Requires-Dist: redis >=4.1.2
Requires-Dist: toml >=0.10.2
Requires-Dist: wheel >=0.36.2
